eiqlib/__init__.py
eiqlib/eiqcalls.py
eiqlib/eiqjson.py
eiqlib-1.0.0.dist-info/LICENSE
eiqlib-1.0.0.dist-info/METADATA
eiqlib-1.0.0.dist-info/WHEEL
eiqlib-1.0.0.dist-info/top_level.txt
eiqlib-1.0.0.dist-info/RECORD
