Metadata-Version: 2.1
Name: eiqlib
Version: 1.0.0
Summary: A python3 library for interacting with EclecticIQ
Home-page: https://github.com/KPN-CISO/eiqlib
Author: Sebastiaan Groot
Author-email: sebastiaang@kpn-cert.nl
License: UNKNOWN
Platform: UNKNOWN
Classifier: Programming Language :: Python :: 3
Classifier: License :: OSI Approved :: MIT License
Classifier: Operating System :: OS Independent
